{
    "metadata": {
        "operation": "retrieve",
        "provider": "Oxford University Press",
        "schema": "RetrieveEntry"
    },
    "query": "decimation",
    "results": [
        {
            "id": "decimation",
            "language": "en-us",
            "lexicalEntries": [
                {
                    "entries": [
                        {
                            "inflections": [
                                {
                                    "inflectedForm": "decimation"
                                },
                                {
                                    "inflectedForm": "decimations"
                                }
                            ],
                            "pronunciations": [
                                {
                                    "dialects": [
                                        "American English"
                                    ],
                                    "phoneticNotation": "respell",
                                    "phoneticSpelling": "ˌdesəˈmāSH(ə)n"
                                },
                                {
                                    "audioFile": "https://audio.oxforddictionaries.com/en/mp3/decimation_us_1.mp3",
                                    "dialects": [
                                        "American English"
                                    ],
                                    "phoneticNotation": "IPA",
                                    "phoneticSpelling": "ˌdɛsəˈmeɪʃ(ə)n"
                                }
                            ],
                            "senses": [
                                {
                                    "definitions": [
                                        "the killing or destruction of a large proportion of a group or species"
                                    ],
                                    "examples": [
                                        {
                                            "text": "our growing hunger for fish has resulted in the decimation of fish stocks"
                                        },
                                        {
                                            "text": "the decimation of our rainforests"
                                        }
                                    ],
                                    "id": "m_en_gbus0256660.006",
                                    "semanticClasses": [
                                        {
                                            "id": "destruction",
                                            "text": "Destruction"
                                        }
                                    ],
                                    "shortDefinitions": [
                                        "killing or destruction of large proportion of group"
                                    ],
                                    "subsenses": [
                                        {
                                            "definitions": [
                                                "a drastic reduction in the strength or effectiveness of something"
                                            ],
                                            "examples": [
                                                {
                                                    "text": "we need to halt the decimation of this country's manufacturing base"
                                                },
                                                {
                                                    "text": "economic and financial decimation from two world wars"
                                                }
                                            ],
                                            "id": "m_en_gbus0256660.009",
                                            "semanticClasses": [
                                                {
                                                    "id": "decrease",
                                                    "text": "Decrease"
                                                }
                                            ],
                                            "shortDefinitions": [
                                                "drastic reduction in strength or effectiveness of something"
                                            ]
                                        }
                                    ]
                                },
                                {
                                    "definitions": [
                                        "the killing of one in every ten of a group of people as a punishment for the whole group (originally with reference to a mutinous Roman legion)."
                                    ],
                                    "domainClasses": [
                                        {
                                            "id": "military",
                                            "text": "Military"
                                        }
                                    ],
                                    "id": "m_en_gbus0256660.011",
                                    "registers": [
                                        {
                                            "id": "historical",
                                            "text": "Historical"
                                        }
                                    ],
                                    "semanticClasses": [
                                        {
                                            "id": "killing",
                                            "text": "Killing"
                                        }
                                    ],
                                    "shortDefinitions": [
                                        "killing of one in every ten of group as punishment for whole group"
                                    ]
                                }
                            ]
                        }
                    ],
                    "language": "en-us",
                    "lexicalCategory": {
                        "id": "noun",
                        "text": "Noun"
                    },
                    "text": "decimation"
                }
            ],
            "type": "headword",
            "word": "decimation"
        }
    ]
}