{
    "metadata": {
        "operation": "retrieve",
        "provider": "Oxford University Press",
        "schema": "RetrieveEntry"
    },
    "query": "layperson",
    "results": [
        {
            "id": "layperson",
            "language": "en-us",
            "lexicalEntries": [
                {
                    "entries": [
                        {
                            "inflections": [
                                {
                                    "grammaticalFeatures": [
                                        {
                                            "id": "plural",
                                            "text": "Plural",
                                            "type": "Number"
                                        }
                                    ],
                                    "inflectedForm": "laypeople"
                                },
                                {
                                    "inflectedForm": "laypeople"
                                },
                                {
                                    "inflectedForm": "layperson"
                                },
                                {
                                    "inflectedForm": "lay-people"
                                },
                                {
                                    "inflectedForm": "lay-person"
                                }
                            ],
                            "pronunciations": [
                                {
                                    "dialects": [
                                        "American English"
                                    ],
                                    "phoneticNotation": "respell",
                                    "phoneticSpelling": "ˈlāˌpərs(ə)n"
                                },
                                {
                                    "audioFile": "https://audio.oxforddictionaries.com/en/mp3/layperson_us_1.mp3",
                                    "dialects": [
                                        "American English"
                                    ],
                                    "phoneticNotation": "IPA",
                                    "phoneticSpelling": "ˈleɪˌpərs(ə)n"
                                }
                            ],
                            "senses": [
                                {
                                    "definitions": [
                                        "a nonordained member of a church."
                                    ],
                                    "domainClasses": [
                                        {
                                            "id": "ecclesiastical",
                                            "text": "Ecclesiastical"
                                        }
                                    ],
                                    "id": "m_en_gbus0569650.012",
                                    "semanticClasses": [
                                        {
                                            "id": "christian",
                                            "text": "Christian"
                                        }
                                    ],
                                    "shortDefinitions": [
                                        "nonordained member of church"
                                    ],
                                    "subsenses": [
                                        {
                                            "definitions": [
                                                "a person without professional or specialized knowledge in a particular subject."
                                            ],
                                            "id": "m_en_gbus0569650.013",
                                            "semanticClasses": [
                                                {
                                                    "id": "person",
                                                    "text": "Person"
                                                }
                                            ],
                                            "shortDefinitions": [
                                                "person without professional or specialized knowledge in particular subject"
                                            ],
                                            "synonyms": [
                                                {
                                                    "language": "en",
                                                    "text": "non-expert"
                                                },
                                                {
                                                    "language": "en",
                                                    "text": "layman"
                                                },
                                                {
                                                    "language": "en",
                                                    "text": "non-professional"
                                                },
                                                {
                                                    "language": "en",
                                                    "text": "amateur"
                                                },
                                                {
                                                    "language": "en",
                                                    "text": "non-specialist"
                                                },
                                                {
                                                    "language": "en",
                                                    "text": "man in the street"
                                                },
                                                {
                                                    "language": "en",
                                                    "text": "man on the street"
                                                }
                                            ],
                                            "thesaurusLinks": [
                                                {
                                                    "entry_id": "layperson",
                                                    "sense_id": "t_en_gb0008610.002"
                                                }
                                            ]
                                        }
                                    ],
                                    "synonyms": [
                                        {
                                            "language": "en",
                                            "text": "unordained person"
                                        },
                                        {
                                            "language": "en",
                                            "text": "member of the congregation"
                                        },
                                        {
                                            "language": "en",
                                            "text": "parishioner"
                                        }
                                    ],
                                    "thesaurusLinks": [
                                        {
                                            "entry_id": "layperson",
                                            "sense_id": "t_en_gb0008610.001"
                                        }
                                    ]
                                }
                            ]
                        }
                    ],
                    "language": "en-us",
                    "lexicalCategory": {
                        "id": "noun",
                        "text": "Noun"
                    },
                    "text": "layperson"
                }
            ],
            "type": "headword",
            "word": "layperson"
        }
    ]
}